setup.cfg
setup.py
econlog/__init__.py
econlog/__version__.py
econlog/econlog.py
econlog.egg-info/PKG-INFO
econlog.egg-info/SOURCES.txt
econlog.egg-info/dependency_links.txt
econlog.egg-info/top_level.txt