Metadata-Version: 1.1
Name: econlog
Version: 1.1
Summary: Show electronic construction log entries.
Home-page: https://github.com/kovacsbalu/econlog
Author: Balint Kovacs
Author-email: kovacsbalu@gmail.com
License: GNU GPL v3
Download-URL: https://github.com/kovacsbalu/econlog/tarball/1.1
Keywords: econlog,enaplo
Platform: UNKNOWN
